worklet/__init__.py
worklet/__main__.py
worklet/py.typed
worklet/executor/__init__.py
worklet/executor/async_executor.py
worklet/executor/base_executor.py
worklet/executor/exceptions.py
worklet/executor/factory.py
worklet/executor/models.py
worklet/kafka/__init__.py
worklet/kafka/consumer/__init__.py
worklet/kafka/consumer/kafka_consumer.py
worklet/kafka/consumer/models.py
worklet/kafka/producer/__init__.py
worklet/kafka/producer/kafka_producer.py
worklet/kafka/producer/models.py
worklet/portal/__init__.py
worklet/portal/models.py
worklet/portal/portal.py
worklet/portal/teleporter.py
worklet/tracker/__init__.py
worklet/tracker/base_tracker.py
worklet/tracker/factory.py
worklet/tracker/in_memory_tracker.py
worklet/tracker/models.py
worklet/tracker/redis_tracker.py
worklet/utils/__init__.py
worklet/utils/autodiscovery.py
worklet/utils/circuit_breaker.py
worklet/utils/func.py
worklet/utils/singleton.py
worklet/worker/__init__.py
worklet/worker/errors.py
worklet/worker/models.py
worklet/worker/runtime.py
worklet/worker/worker.py
worklet/worklet/__init__.py
worklet/worklet/models.py
worklet/worklet/registry.py
worklet/worklet/worklet.py
worklet-0.1.7.dist-info/licenses/LICENSE
worklet-0.1.7.dist-info/METADATA
worklet-0.1.7.dist-info/WHEEL
worklet-0.1.7.dist-info/entry_points.txt
worklet-0.1.7.dist-info/top_level.txt
worklet-0.1.7.dist-info/RECORD
