Metadata-Version: 2.4
Name: worklet
Version: 0.1.7
Summary: A high-performance distributed task framework for Python powered by Kafka.
Author-email: Troy M Jose <troymjose@gmail.com>
License: MIT License
Project-URL: Homepage, https://github.com/troymjose/worklet
Project-URL: Documentation, https://github.com/troymjose/worklet
Project-URL: Issues, https://github.com/troymjose/worklet/issues
Keywords: worklet,asyncio,kafka,distributed,background,queue
Classifier: Development Status :: 1 - Planning
Classifier: Intended Audience :: Developers
Classifier: License :: OSI Approved :: MIT License
Classifier: Operating System :: OS Independent
Classifier: Programming Language :: Python :: 3.11
Classifier: Programming Language :: Python :: 3.12
Classifier: Topic :: Software Development :: Libraries
Requires-Python: >=3.9
License-File: LICENSE
Requires-Dist: confluent-kafka
Requires-Dist: orjson
Provides-Extra: dev
Requires-Dist: pytest; extra == "dev"
Requires-Dist: pytest-asyncio; extra == "dev"
Requires-Dist: ruff; extra == "dev"
Requires-Dist: black; extra == "dev"
Requires-Dist: mkdocs; extra == "dev"
Requires-Dist: mkdocs-material; extra == "dev"
Requires-Dist: mkdocstrings[python]; extra == "dev"
Requires-Dist: sphinx; extra == "dev"
Requires-Dist: sphinx-autodoc-typehints; extra == "dev"
Requires-Dist: furo; extra == "dev"
Dynamic: license-file
